jirafs_matplotlib/__init__.py
jirafs_matplotlib/plugin.py
jirafs_matplotlib-1.0.3.dist-info/METADATA
jirafs_matplotlib-1.0.3.dist-info/WHEEL
jirafs_matplotlib-1.0.3.dist-info/entry_points.txt
jirafs_matplotlib-1.0.3.dist-info/top_level.txt
jirafs_matplotlib-1.0.3.dist-info/RECORD
